glasses/__init__.py
glasses/data/__init__.py
glasses/data/visualisation/__init__.py
glasses/interpretability/GradCam.py
glasses/interpretability/Interpretability.py
glasses/interpretability/SaliencyMap.py
glasses/interpretability/__init__.py
glasses/interpretability/utils.py
glasses/models/AutoConfig.py
glasses/models/AutoModel.py
glasses/models/__init__.py
glasses/models/base/__init__.py
glasses/models/base/protocols.py
glasses/models/classification/__init__.py
glasses/models/classification/alexnet/__init__.py
glasses/models/classification/deit/__init__.py
glasses/models/classification/densenet/__init__.py
glasses/models/classification/efficientnet/__init__.py
glasses/models/classification/fishnet/__init__.py
glasses/models/classification/mobilenet/__init__.py
glasses/models/classification/regnet/__init__.py
glasses/models/classification/resnest/__init__.py
glasses/models/classification/resnet/__init__.py
glasses/models/classification/resnetxt/__init__.py
glasses/models/classification/senet/__init__.py
glasses/models/classification/vgg/__init__.py
glasses/models/classification/vit/__init__.py
glasses/models/classification/wide_resnet/__init__.py
glasses/models/segmentation/__init__.py
glasses/models/segmentation/base/__init__.py
glasses/models/segmentation/fpn/__init__.py
glasses/models/segmentation/unet/__init__.py
glasses/models/utils/__init__.py
glasses/models/utils/scaler.py
glasses/nn/__init__.py
glasses/nn/regularization.py
glasses/nn/activation/__init__.py
glasses/nn/att/__init__.py
glasses/nn/blocks/__init__.py
glasses/nn/blocks/residuals.py
glasses/nn/pool/SpatialPyramidPool.py
glasses/nn/pool/__init__.py
glasses/utils/ModuleTransfer.py
glasses/utils/PretrainedWeightsProvider.py
glasses/utils/Storage.py
glasses/utils/Tracker.py
glasses/utils/__init__.py
glasses-0.0.6.dist-info/LICENSE
glasses-0.0.6.dist-info/METADATA
glasses-0.0.6.dist-info/WHEEL
glasses-0.0.6.dist-info/top_level.txt
glasses-0.0.6.dist-info/RECORD
