Metadata-Version: 2.1
Name: glasses
Version: 0.0.6
Summary: Compact, concise and customizable deep learning computer vision
Home-page: https://github.com/FrancescoSaverioZuppichini/glasses
Author: Francesco Saverio Zuppichini & Francesco Cicala
Author-email: francesco.zuppichini@gmail.com
License: UNKNOWN
Platform: UNKNOWN
Classifier: Programming Language :: Python :: 3
Classifier: License :: OSI Approved :: MIT License
Classifier: Operating System :: OS Independent
Requires-Python: >=3.7
